pycycling/__init__.py
pycycling/battery_service.py
pycycling/cycling_power_service.py
pycycling/cycling_speed_cadence_service.py
pycycling/fitness_machine_service.py
pycycling/heart_rate_service.py
pycycling/rear_view_radar.py
pycycling/rizer.py
pycycling/sterzo.py
pycycling/tacx_trainer_control.py
pycycling/data/__init__.py
pycycling/data/sterzo-challenge-codes.dat
pycycling/ftms_parsers/__init__.py
pycycling/ftms_parsers/control_point.py
pycycling/ftms_parsers/fitness_machine_feature.py
pycycling/ftms_parsers/fitness_machine_status.py
pycycling/ftms_parsers/indoor_bike_data.py
pycycling/ftms_parsers/training_status.py
test/__init__.py
test/test_battery_service.py
test/test_cycling_power_service.py
test/test_cycling_speed_cadence_service.py
test/test_heart_rate_service.py
test/test_rear_view_radar.py
pycycling-0.4.0.dist-info/LICENSE
pycycling-0.4.0.dist-info/METADATA
pycycling-0.4.0.dist-info/WHEEL
pycycling-0.4.0.dist-info/top_level.txt
pycycling-0.4.0.dist-info/RECORD
