Metadata-Version: 2.1
Name: pycycling
Version: 0.4.0
Summary: A Python package for interacting with Bluetooth Low Energy (BLE) compatible bike trainers, power meters, radars and heart rate monitors
Home-page: https://github.com/zacharyedwardbull/pycycling
Author: Zachary Bull
Author-email: zacharyedwardbull@gmail.com
Classifier: Programming Language :: Python :: 3
Classifier: License :: OSI Approved :: MIT License
Classifier: Operating System :: OS Independent
Requires-Python: >=3.7
License-File: LICENSE
Requires-Dist: bleak
